counter/counter.v
module counter (
    input  wire       clk,   // 時脈訊號
    input  wire       rst_n, // 低電位重置訊號 (Reset Active Low)
    output reg [7:0]  out    // 8 位元輸出 (0~255)
);

    // 順序邏輯：在時鐘上升緣觸發
    always @(posedge clk or negedge rst_n) begin
        if (!rst_n) begin
            out <= 8'd0;     // 如果重置，歸零
        end else begin
            out <= out + 1'b1; // 否則每個時鐘週期加 1
        end
    end

endmodule

counter/counter_tb.v
`timescale 1ns/1ps // 時間單位/精準度

module counter_tb;

    // 定義輸入為 reg，輸出為 wire
    reg        clk;
    reg        rst_n;
    wire [7:0] out;

    // 載入剛才寫的 counter 模組 (D.U.T: Device Under Test)
    counter uut (
        .clk(clk),
        .rst_n(rst_n),
        .out(out)
    );

    // 產生時鐘訊號：每 5ns 翻轉一次，所以週期是 10ns (100MHz)
    always #5 clk = ~clk;

    initial begin
        // 1. 設定產出波形檔，給 GTKWave 看
        $dumpfile("counter_test.vcd");
        $dumpvars(0, counter_tb);

        // 2. 初始化訊號
        clk = 0;
        rst_n = 0;      // 一開始先重置
        #20 rst_n = 1;  // 過 20ns 後放開重置，讓它開始跑

        // 3. 跑一段時間後停止
        #200 $finish;
    end

endmodule

counter/counter_test.vcd
$date
	Fri Mar 13 21:02:10 2026
$end
$version
	Icarus Verilog
$end
$timescale
	1ps
$end
$scope module counter_tb $end
$var wire 8 ! out [7:0] $end
$var reg 1 " clk $end
$var reg 1 # rst_n $end
$scope module uut $end
$var wire 1 " clk $end
$var wire 1 # rst_n $end
$var reg 8 $ out [7:0] $end
$upscope $end
$upscope $end
$enddefinitions $end
$comment Show the parameter values. $end
$dumpall
$end
#0
$dumpvars
b0 $
0#
0"
b0 !
$end
#5000
1"
#10000
0"
#15000
1"
#20000
0"
1#
#25000
b1 !
b1 $
1"
#30000
0"
#35000
b10 !
b10 $
1"
#40000
0"
#45000
b11 !
b11 $
1"
#50000
0"
#55000
b100 !
b100 $
1"
#60000
0"
#65000
b101 !
b101 $
1"
#70000
0"
#75000
b110 !
b110 $
1"
#80000
0"
#85000
b111 !
b111 $
1"
#90000
0"
#95000
b1000 !
b1000 $
1"
#100000
0"
#105000
b1001 !
b1001 $
1"
#110000
0"
#115000
b1010 !
b1010 $
1"
#120000
0"
#125000
b1011 !
b1011 $
1"
#130000
0"
#135000
b1100 !
b1100 $
1"
#140000
0"
#145000
b1101 !
b1101 $
1"
#150000
0"
#155000
b1110 !
b1110 $
1"
#160000
0"
#165000
b1111 !
b1111 $
1"
#170000
0"
#175000
b10000 !
b10000 $
1"
#180000
0"
#185000
b10001 !
b10001 $
1"
#190000
0"
#195000
b10010 !
b10010 $
1"
#200000
0"
#205000
b10011 !
b10011 $
1"
#210000
0"
#215000
b10100 !
b10100 $
1"
